quicfire/__init__.py
quicfire/main.py
quicfire/schema.py
quicfire-1.0.1.dist-info/METADATA
quicfire-1.0.1.dist-info/WHEEL
quicfire-1.0.1.dist-info/top_level.txt
quicfire-1.0.1.dist-info/RECORD
